{"dst":{"id":"00054","name":"Одесская 1","create_data_time":"2019-03-26 07:51:45","id_in_1c":"ФР-000054","type_operation":"shipment","destination_type":"store"},"package":{"ФР-00000605":{"ItemDescription":"Ящик п/е 1,26кг 600*400*160мм","UnitOfMeasure":"шт","Quantity":"0"},"ФР-00000606":{"ItemDescription":"Ящик п/е 1,8 кг 600*400*260мм","UnitOfMeasure":"шт","Quantity":"4"},"ФР-00000607":{"ItemDescription":"Ящик п/е 0,85кг 600*400*75мм","UnitOfMeasure":"шт","Quantity":"0"},"ФР-00000608":{"ItemDescription":"Піддон пласт 12,5 кг 1200*800мм, синій","UnitOfMeasure":"шт","Quantity":"0"},"chicken":{"ФР-00000003":["0"],"ФР-00000005":[0],"ФР-00000010":["0"],"ФР-00000008":["0"],"ФР-00000024":["0"],"ФР-00000026":["0"],"ФР-00000637":["0"],"ФР-00000027":["0"],"ФР-00001041":["0"],"ФР-00000020":["0"],"ФР-00000012":["0"]}},"type_package":{"chicken":{"ФР-00000003":["ФР-00000605"],"ФР-00000005":["ФР-00000605"],"ФР-00000010":["ФР-00000605"],"ФР-00000008":["ФР-00000605"],"ФР-00000024":["ФР-00000605"],"ФР-00000026":["ФР-00000605"],"ФР-00000637":["ФР-00000605"],"ФР-00000027":["ФР-00000605"],"ФР-00001041":["ФР-00000605"],"ФР-00000020":["ФР-00000605"],"ФР-00000012":["ФР-00000605"]}},"type":"shipment","shipment":{"chicken":{"ФР-00000003":["0003.96"],"ФР-00000005":[3.964],"ФР-00000010":["0006.70"],"ФР-00000008":["0004.30"],"ФР-00000024":["0005.04"],"ФР-00000026":["0007.58"],"ФР-00000637":["0006.98"],"ФР-00000027":["0005.54"],"ФР-00001041":["0005.52"],"ФР-00000020":["0003.84"],"ФР-00000012":["0007.82"]}},"price_product":{"chicken":{"ФР-00000003":{"Description":"Крило кур-бр, н/ф охол  (нефас 20 кг)","Price":67.9},"ФР-00000005":{"Description":"Печінка  кур-бр охол  (нефас 10 кг)","Price":65.9},"ФР-00000010":{"Description":"Филе  кур-бр, н/ф охол  (нефас 20 кг)","Price":102.9},"ФР-00000008":{"Description":"Шия  кур-бр охол  (нефас 10 кг)\n","Price":23.9},"ФР-00000024":{"Description":"Фарш мясной\n","Price":76.9},"ФР-00000026":{"Description":"Хребты кур-бр. н/ф охл\n","Price":17.9},"ФР-00000637":{"Description":"Крило (плеч. част) кур.-бр, н/ф охол (нефас 20кг)","Price":51.9},"ФР-00000027":{"Description":"Кости кур-бр. н/ф охл","Price":9.9},"ФР-00001041":{"Description":"Каркас чищеный перед. частини кур-бр. н/ф  охл","Price":12.9},"ФР-00000020":{"Description":"Бедро с хребтом кур-бр. н/ф  охл","Price":48.9},"ФР-00000012":{"Description":"Четверт задня  кур-бр, н/ф охол  (нефас 20 кг)","Price":48.9}}},"contragent_name":{"chicken":{"ФР-00000003":"Одесская 1","ФР-00000005":"Одесская 1","ФР-00000010":"Одесская 1","ФР-00000008":"Одесская 1","ФР-00000024":"Одесская 1","ФР-00000026":"Одесская 1","ФР-00000637":"Одесская 1","ФР-00000027":"Одесская 1","ФР-00001041":"Одесская 1","ФР-00000020":"Одесская 1","ФР-00000012":"Одесская 1"}},"ItemDescription":{"chicken":{"ФР-00000003":"Крило кур-бр, н/ф охол  (нефас 20 кг)","ФР-00000005":"Печінка  кур-бр охол  (нефас 10 кг)","ФР-00000010":"Филе  кур-бр, н/ф охол  (нефас 20 кг)","ФР-00000008":"Шия  кур-бр охол  (нефас 10 кг)\n","ФР-00000024":"Фарш мясной\n","ФР-00000026":"Хребты кур-бр. н/ф охл\n","ФР-00000637":"Крило (плеч. част) кур.-бр, н/ф охол (нефас 20кг)","ФР-00000027":"Кости кур-бр. н/ф охл","ФР-00001041":"Каркас чищеный перед. частини кур-бр. н/ф  охл","ФР-00000020":"Бедро с хребтом кур-бр. н/ф  охл","ФР-00000012":"Четверт задня  кур-бр, н/ф охол  (нефас 20 кг)"}},"contact_person":{"chicken":{}},"contragent_descr":{"chicken":{"ФР-00000003":"","ФР-00000005":"","ФР-00000010":"","ФР-00000008":"","ФР-00000024":"","ФР-00000026":"","ФР-00000637":"","ФР-00000027":"","ФР-00001041":"","ФР-00000020":"","ФР-00000012":""}}}